arora/__init__.py
arora/find_features.py
arora/core/__init__.py
arora/core/get_signals.py
arora/core/segmentation.py
arora/filter/EEG_freqbands.py
arora/filter/__init__.py
arora/filter/bandpass.py
arora/filter/pass_filter.py
arora/filter/upper_lower_signal_envelopes.py
arora/math/__init__.py
arora/math/iqrstandardize.py
arora/math/mean.py
arora/math/standardize.py
arora/math/std.py
arora/plot/__init__.py
arora/plot/distributionpie.py
arora/plot/hypnogram.py
arora/reader/__init__.py
arora/reader/get_edf.py
arora/reader/read_mat.py
arora/reader/sleepdata.py
arora/segmentation/__init__.py
arora/segmentation/get_segment.py
arora/segmentation/segment_fs.py
arora/signals/__init__.py
arora/signals/fourier.py
arora/signals/lower_frequency.py
arora/signals/resample.py
arora/signals/wavelet.py
arora/signals/welch.py
tests/__init__.py
tests/config.py
tests/test_bandpass.py
tests/test_example.py
tests/test_filtering.py
tests/test_lower_frequency.py
tests/test_math.py
arora-1.0.2.dist-info/METADATA
arora-1.0.2.dist-info/WHEEL
arora-1.0.2.dist-info/top_level.txt
arora-1.0.2.dist-info/RECORD
