Metadata-Version: 2.1
Name: arora
Version: 1.0.2
Summary: A tool for sleep researcher to preprocess, work, analyze and visualize data
Author: Sleep Revolution
Author-email: sleeprevolution@ru.is
Project-URL: Documentation, https://sleep-revolution.gitlab.io/sleepy/v0.1.2/
Classifier: Development Status :: 3 - Alpha
Classifier: Intended Audience :: Science/Research
Classifier: Operating System :: OS Independent
Classifier: Programming Language :: Python :: 3.8
Requires-Python: >=3.8
Requires-Dist: numpy
Requires-Dist: pandas
Requires-Dist: pyEDFlib
Requires-Dist: scipy
